{"individual":[{"courseName":"LPS 304 - Section 601","courseId":"LPS-304-601-2241","instructorName":"Laraway,Kelly H.","courseSem":"Spring '24","grades":{"A":{"raw":10,"percentage":"76.9%"},"B":{"raw":1,"percentage":"7.7%"},"C":{"raw":0,"percentage":"0%"},"D":{"raw":0,"percentage":"0%"},"F":{"raw":0,"percentage":"0%"},"S":{"raw":0,"percentage":"0%"},"U":{"raw":1,"percentage":"7.7%"},"IN":{"raw":0,"percentage":"0%"},"LA":{"raw":0,"percentage":"0%"},"AU":{"raw":0,"percentage":"0%"},"NR":{"raw":0,"percentage":"0%"},"W":{"raw":1,"percentage":"7.7%"},"TOTAL":{"raw":13,"percentage":"100%"}},"googleChart":{"cols":[{"id":"Name","label":"Name","type":"string"},{"id":"Value","label":"Value","type":"number"}],"rows":[{"c":[{"v":"A"},{"v":10}]},{"c":[{"v":"B"},{"v":1}]},{"c":[{"v":"C"},{"v":0}]},{"c":[{"v":"D"},{"v":0}]},{"c":[{"v":"F"},{"v":0}]},{"c":[{"v":"S"},{"v":0}]},{"c":[{"v":"U"},{"v":1}]},{"c":[{"v":"IN"},{"v":0}]},{"c":[{"v":"LA"},{"v":0}]},{"c":[{"v":"AU"},{"v":0}]},{"c":[{"v":"NR"},{"v":0}]},{"c":[{"v":"W"},{"v":1}]}]}},{"courseName":"LPS 304 - Section 601","courseId":"LPS-304-601-2231","instructorName":"Laraway,Kelly H.","courseSem":"Spring '23","grades":{"A":{"raw":11,"percentage":"73.3%"},"B":{"raw":1,"percentage":"6.7%"},"C":{"raw":0,"percentage":"0%"},"D":{"raw":0,"percentage":"0%"},"F":{"raw":2,"percentage":"13.3%"},"S":{"raw":0,"percentage":"0%"},"U":{"raw":0,"percentage":"0%"},"IN":{"raw":0,"percentage":"0%"},"LA":{"raw":0,"percentage":"0%"},"AU":{"raw":0,"percentage":"0%"},"NR":{"raw":1,"percentage":"6.7%"},"W":{"raw":0,"percentage":"0%"},"TOTAL":{"raw":15,"percentage":"100%"}},"googleChart":{"cols":[{"id":"Name","label":"Name","type":"string"},{"id":"Value","label":"Value","type":"number"}],"rows":[{"c":[{"v":"A"},{"v":11}]},{"c":[{"v":"B"},{"v":1}]},{"c":[{"v":"C"},{"v":0}]},{"c":[{"v":"D"},{"v":0}]},{"c":[{"v":"F"},{"v":2}]},{"c":[{"v":"S"},{"v":0}]},{"c":[{"v":"U"},{"v":0}]},{"c":[{"v":"IN"},{"v":0}]},{"c":[{"v":"LA"},{"v":0}]},{"c":[{"v":"AU"},{"v":0}]},{"c":[{"v":"NR"},{"v":1}]},{"c":[{"v":"W"},{"v":0}]}]}},{"courseName":"LPS 304 - Section 601","courseId":"LPS-304-601-2221","instructorName":"Laraway,Kelly H.","courseSem":"Spring '22","grades":{"A":{"raw":8,"percentage":"72.7%"},"B":{"raw":0,"percentage":"0%"},"C":{"raw":0,"percentage":"0%"},"D":{"raw":0,"percentage":"0%"},"F":{"raw":1,"percentage":"9.1%"},"S":{"raw":0,"percentage":"0%"},"U":{"raw":1,"percentage":"9.1%"},"IN":{"raw":0,"percentage":"0%"},"LA":{"raw":0,"percentage":"0%"},"AU":{"raw":0,"percentage":"0%"},"NR":{"raw":0,"percentage":"0%"},"W":{"raw":1,"percentage":"9.1%"},"TOTAL":{"raw":11,"percentage":"100%"}},"googleChart":{"cols":[{"id":"Name","label":"Name","type":"string"},{"id":"Value","label":"Value","type":"number"}],"rows":[{"c":[{"v":"A"},{"v":8}]},{"c":[{"v":"B"},{"v":0}]},{"c":[{"v":"C"},{"v":0}]},{"c":[{"v":"D"},{"v":0}]},{"c":[{"v":"F"},{"v":1}]},{"c":[{"v":"S"},{"v":0}]},{"c":[{"v":"U"},{"v":1}]},{"c":[{"v":"IN"},{"v":0}]},{"c":[{"v":"LA"},{"v":0}]},{"c":[{"v":"AU"},{"v":0}]},{"c":[{"v":"NR"},{"v":0}]},{"c":[{"v":"W"},{"v":1}]}]}}],"composite":{"googleChartPie":{"cols":[{"id":"Name","label":"Name","type":"string"},{"id":"Value","label":"Value","type":"number"}],"rows":[{"c":[{"v":"A"},{"v":29}]},{"c":[{"v":"B"},{"v":2}]},{"c":[{"v":"C"},{"v":0}]},{"c":[{"v":"D"},{"v":0}]},{"c":[{"v":"F"},{"v":3}]}]},"googleChartBar":{"cols":[{"id":"Class","label":"Class","type":"string"},{"id":"A","label":"A","type":"number"},{"id":"B","label":"B","type":"number"},{"id":"C","label":"C","type":"number"},{"id":"D","label":"D","type":"number"},{"id":"F","label":"F","type":"number"}],"rows":[{"c":[{"v":"Spring '24, Section 601"},{"v":10},{"v":1},{"v":0},{"v":0},{"v":0}]},{"c":[{"v":"Spring '23, Section 601"},{"v":11},{"v":1},{"v":0},{"v":0},{"v":2}]},{"c":[{"v":"Spring '22, Section 601"},{"v":8},{"v":0},{"v":0},{"v":0},{"v":1}]}]},"grades":{"A":{"raw":29,"percentage":"74.4%"},"B":{"raw":2,"percentage":"5.1%"},"C":{"raw":0,"percentage":"0%"},"D":{"raw":0,"percentage":"0%"},"F":{"raw":3,"percentage":"7.7%"},"S":{"raw":0,"percentage":"0%"},"U":{"raw":2,"percentage":"5.1%"},"IN":{"raw":0,"percentage":"0%"},"LA":{"raw":0,"percentage":"0%"},"AU":{"raw":0,"percentage":"0%"},"NR":{"raw":1,"percentage":"2.6%"},"W":{"raw":2,"percentage":"5.1%"},"TOTAL":{"raw":39,"percentage":"100%"}},"pieTitle":"Composite Grade Distribution for Selected Parameters","pieInfo":"Showing only letter grades"}}