{"individual":[{"courseName":"AFS 444 - Section 601","courseId":"AFS-444-601-2248","instructorName":"Graham,Frances D","courseSem":"Fall '24","grades":{"A":{"raw":46,"percentage":"83.6%"},"B":{"raw":9,"percentage":"16.4%"},"C":{"raw":0,"percentage":"0%"},"D":{"raw":0,"percentage":"0%"},"F":{"raw":0,"percentage":"0%"},"S":{"raw":0,"percentage":"0%"},"U":{"raw":0,"percentage":"0%"},"IN":{"raw":0,"percentage":"0%"},"LA":{"raw":0,"percentage":"0%"},"AU":{"raw":0,"percentage":"0%"},"NR":{"raw":0,"percentage":"0%"},"W":{"raw":0,"percentage":"0%"},"TOTAL":{"raw":55,"percentage":"100%"}},"googleChart":{"cols":[{"id":"Name","label":"Name","type":"string"},{"id":"Value","label":"Value","type":"number"}],"rows":[{"c":[{"v":"A"},{"v":46}]},{"c":[{"v":"B"},{"v":9}]},{"c":[{"v":"C"},{"v":0}]},{"c":[{"v":"D"},{"v":0}]},{"c":[{"v":"F"},{"v":0}]},{"c":[{"v":"S"},{"v":0}]},{"c":[{"v":"U"},{"v":0}]},{"c":[{"v":"IN"},{"v":0}]},{"c":[{"v":"LA"},{"v":0}]},{"c":[{"v":"AU"},{"v":0}]},{"c":[{"v":"NR"},{"v":0}]},{"c":[{"v":"W"},{"v":0}]}]}},{"courseName":"AFS 444 - Section 601","courseId":"AFS-444-601-2241","instructorName":"Graham,Frances D","courseSem":"Spring '24","grades":{"A":{"raw":19,"percentage":"63.3%"},"B":{"raw":9,"percentage":"30%"},"C":{"raw":0,"percentage":"0%"},"D":{"raw":0,"percentage":"0%"},"F":{"raw":2,"percentage":"6.7%"},"S":{"raw":0,"percentage":"0%"},"U":{"raw":0,"percentage":"0%"},"IN":{"raw":0,"percentage":"0%"},"LA":{"raw":0,"percentage":"0%"},"AU":{"raw":0,"percentage":"0%"},"NR":{"raw":0,"percentage":"0%"},"W":{"raw":0,"percentage":"0%"},"TOTAL":{"raw":30,"percentage":"100%"}},"googleChart":{"cols":[{"id":"Name","label":"Name","type":"string"},{"id":"Value","label":"Value","type":"number"}],"rows":[{"c":[{"v":"A"},{"v":19}]},{"c":[{"v":"B"},{"v":9}]},{"c":[{"v":"C"},{"v":0}]},{"c":[{"v":"D"},{"v":0}]},{"c":[{"v":"F"},{"v":2}]},{"c":[{"v":"S"},{"v":0}]},{"c":[{"v":"U"},{"v":0}]},{"c":[{"v":"IN"},{"v":0}]},{"c":[{"v":"LA"},{"v":0}]},{"c":[{"v":"AU"},{"v":0}]},{"c":[{"v":"NR"},{"v":0}]},{"c":[{"v":"W"},{"v":0}]}]}},{"courseName":"AFS 444 - Section 601","courseId":"AFS-444-601-2238","instructorName":"Graham,Frances D","courseSem":"Fall '23","grades":{"A":{"raw":43,"percentage":"79.6%"},"B":{"raw":8,"percentage":"14.8%"},"C":{"raw":1,"percentage":"1.9%"},"D":{"raw":0,"percentage":"0%"},"F":{"raw":2,"percentage":"3.7%"},"S":{"raw":0,"percentage":"0%"},"U":{"raw":0,"percentage":"0%"},"IN":{"raw":0,"percentage":"0%"},"LA":{"raw":0,"percentage":"0%"},"AU":{"raw":0,"percentage":"0%"},"NR":{"raw":0,"percentage":"0%"},"W":{"raw":0,"percentage":"0%"},"TOTAL":{"raw":54,"percentage":"100%"}},"googleChart":{"cols":[{"id":"Name","label":"Name","type":"string"},{"id":"Value","label":"Value","type":"number"}],"rows":[{"c":[{"v":"A"},{"v":43}]},{"c":[{"v":"B"},{"v":8}]},{"c":[{"v":"C"},{"v":1}]},{"c":[{"v":"D"},{"v":0}]},{"c":[{"v":"F"},{"v":2}]},{"c":[{"v":"S"},{"v":0}]},{"c":[{"v":"U"},{"v":0}]},{"c":[{"v":"IN"},{"v":0}]},{"c":[{"v":"LA"},{"v":0}]},{"c":[{"v":"AU"},{"v":0}]},{"c":[{"v":"NR"},{"v":0}]},{"c":[{"v":"W"},{"v":0}]}]}},{"courseName":"AFS 444 - Section 601","courseId":"AFS-444-601-2231","instructorName":"Graham,Frances D","courseSem":"Spring '23","grades":{"A":{"raw":18,"percentage":"64.3%"},"B":{"raw":7,"percentage":"25%"},"C":{"raw":2,"percentage":"7.1%"},"D":{"raw":1,"percentage":"3.6%"},"F":{"raw":0,"percentage":"0%"},"S":{"raw":0,"percentage":"0%"},"U":{"raw":0,"percentage":"0%"},"IN":{"raw":0,"percentage":"0%"},"LA":{"raw":0,"percentage":"0%"},"AU":{"raw":0,"percentage":"0%"},"NR":{"raw":0,"percentage":"0%"},"W":{"raw":0,"percentage":"0%"},"TOTAL":{"raw":28,"percentage":"100%"}},"googleChart":{"cols":[{"id":"Name","label":"Name","type":"string"},{"id":"Value","label":"Value","type":"number"}],"rows":[{"c":[{"v":"A"},{"v":18}]},{"c":[{"v":"B"},{"v":7}]},{"c":[{"v":"C"},{"v":2}]},{"c":[{"v":"D"},{"v":1}]},{"c":[{"v":"F"},{"v":0}]},{"c":[{"v":"S"},{"v":0}]},{"c":[{"v":"U"},{"v":0}]},{"c":[{"v":"IN"},{"v":0}]},{"c":[{"v":"LA"},{"v":0}]},{"c":[{"v":"AU"},{"v":0}]},{"c":[{"v":"NR"},{"v":0}]},{"c":[{"v":"W"},{"v":0}]}]}}],"composite":{"googleChartPie":{"cols":[{"id":"Name","label":"Name","type":"string"},{"id":"Value","label":"Value","type":"number"}],"rows":[{"c":[{"v":"A"},{"v":126}]},{"c":[{"v":"B"},{"v":33}]},{"c":[{"v":"C"},{"v":3}]},{"c":[{"v":"D"},{"v":1}]},{"c":[{"v":"F"},{"v":4}]}]},"googleChartBar":{"cols":[{"id":"Class","label":"Class","type":"string"},{"id":"A","label":"A","type":"number"},{"id":"B","label":"B","type":"number"},{"id":"C","label":"C","type":"number"},{"id":"D","label":"D","type":"number"},{"id":"F","label":"F","type":"number"}],"rows":[{"c":[{"v":"Fall '24, Section 601"},{"v":46},{"v":9},{"v":0},{"v":0},{"v":0}]},{"c":[{"v":"Spring '24, Section 601"},{"v":19},{"v":9},{"v":0},{"v":0},{"v":2}]},{"c":[{"v":"Fall '23, Section 601"},{"v":43},{"v":8},{"v":1},{"v":0},{"v":2}]},{"c":[{"v":"Spring '23, Section 601"},{"v":18},{"v":7},{"v":2},{"v":1},{"v":0}]}]},"grades":{"A":{"raw":126,"percentage":"75.4%"},"B":{"raw":33,"percentage":"19.8%"},"C":{"raw":3,"percentage":"1.8%"},"D":{"raw":1,"percentage":"0.6%"},"F":{"raw":4,"percentage":"2.4%"},"S":{"raw":0,"percentage":"0%"},"U":{"raw":0,"percentage":"0%"},"IN":{"raw":0,"percentage":"0%"},"LA":{"raw":0,"percentage":"0%"},"AU":{"raw":0,"percentage":"0%"},"NR":{"raw":0,"percentage":"0%"},"W":{"raw":0,"percentage":"0%"},"TOTAL":{"raw":167,"percentage":"100%"}},"pieTitle":"Composite Grade Distribution for Selected Parameters","pieInfo":"Showing only letter grades"}}