{"individual":[{"courseName":"M 300 - Section 001","courseId":"M-300-001-2148","instructorName":"Brown,Lauren H.","courseSem":"Fall '14","grades":{"A":{"raw":51,"percentage":"96.2%"},"B":{"raw":2,"percentage":"3.8%"},"C":{"raw":0,"percentage":"0%"},"D":{"raw":0,"percentage":"0%"},"F":{"raw":0,"percentage":"0%"},"S":{"raw":0,"percentage":"0%"},"U":{"raw":0,"percentage":"0%"},"IN":{"raw":0,"percentage":"0%"},"LA":{"raw":0,"percentage":"0%"},"AU":{"raw":0,"percentage":"0%"},"NR":{"raw":0,"percentage":"0%"},"W":{"raw":0,"percentage":"0%"},"TOTAL":{"raw":53,"percentage":"100%"}},"googleChart":{"cols":[{"id":"Name","label":"Name","type":"string"},{"id":"Value","label":"Value","type":"number"}],"rows":[{"c":[{"v":"A"},{"v":51}]},{"c":[{"v":"B"},{"v":2}]},{"c":[{"v":"C"},{"v":0}]},{"c":[{"v":"D"},{"v":0}]},{"c":[{"v":"F"},{"v":0}]},{"c":[{"v":"S"},{"v":0}]},{"c":[{"v":"U"},{"v":0}]},{"c":[{"v":"IN"},{"v":0}]},{"c":[{"v":"LA"},{"v":0}]},{"c":[{"v":"AU"},{"v":0}]},{"c":[{"v":"NR"},{"v":0}]},{"c":[{"v":"W"},{"v":0}]}]}},{"courseName":"M 300 - Section 001","courseId":"M-300-001-2138","instructorName":"Brown,Lauren H.","courseSem":"Fall '13","grades":{"A":{"raw":32,"percentage":"88.9%"},"B":{"raw":1,"percentage":"2.8%"},"C":{"raw":0,"percentage":"0%"},"D":{"raw":0,"percentage":"0%"},"F":{"raw":0,"percentage":"0%"},"S":{"raw":3,"percentage":"8.3%"},"U":{"raw":0,"percentage":"0%"},"IN":{"raw":0,"percentage":"0%"},"LA":{"raw":0,"percentage":"0%"},"AU":{"raw":0,"percentage":"0%"},"NR":{"raw":0,"percentage":"0%"},"W":{"raw":0,"percentage":"0%"},"TOTAL":{"raw":36,"percentage":"100%"}},"googleChart":{"cols":[{"id":"Name","label":"Name","type":"string"},{"id":"Value","label":"Value","type":"number"}],"rows":[{"c":[{"v":"A"},{"v":32}]},{"c":[{"v":"B"},{"v":1}]},{"c":[{"v":"C"},{"v":0}]},{"c":[{"v":"D"},{"v":0}]},{"c":[{"v":"F"},{"v":0}]},{"c":[{"v":"S"},{"v":3}]},{"c":[{"v":"U"},{"v":0}]},{"c":[{"v":"IN"},{"v":0}]},{"c":[{"v":"LA"},{"v":0}]},{"c":[{"v":"AU"},{"v":0}]},{"c":[{"v":"NR"},{"v":0}]},{"c":[{"v":"W"},{"v":0}]}]}},{"courseName":"M 300 - Section 001","courseId":"M-300-001-2128","instructorName":"Brown,Lauren H.","courseSem":"Fall '12","grades":{"A":{"raw":34,"percentage":"81%"},"B":{"raw":1,"percentage":"2.4%"},"C":{"raw":0,"percentage":"0%"},"D":{"raw":0,"percentage":"0%"},"F":{"raw":0,"percentage":"0%"},"S":{"raw":7,"percentage":"16.7%"},"U":{"raw":0,"percentage":"0%"},"IN":{"raw":0,"percentage":"0%"},"LA":{"raw":0,"percentage":"0%"},"AU":{"raw":0,"percentage":"0%"},"NR":{"raw":0,"percentage":"0%"},"W":{"raw":0,"percentage":"0%"},"TOTAL":{"raw":42,"percentage":"100%"}},"googleChart":{"cols":[{"id":"Name","label":"Name","type":"string"},{"id":"Value","label":"Value","type":"number"}],"rows":[{"c":[{"v":"A"},{"v":34}]},{"c":[{"v":"B"},{"v":1}]},{"c":[{"v":"C"},{"v":0}]},{"c":[{"v":"D"},{"v":0}]},{"c":[{"v":"F"},{"v":0}]},{"c":[{"v":"S"},{"v":7}]},{"c":[{"v":"U"},{"v":0}]},{"c":[{"v":"IN"},{"v":0}]},{"c":[{"v":"LA"},{"v":0}]},{"c":[{"v":"AU"},{"v":0}]},{"c":[{"v":"NR"},{"v":0}]},{"c":[{"v":"W"},{"v":0}]}]}}],"composite":{"googleChartPie":{"cols":[{"id":"Name","label":"Name","type":"string"},{"id":"Value","label":"Value","type":"number"}],"rows":[{"c":[{"v":"A"},{"v":117}]},{"c":[{"v":"B"},{"v":4}]},{"c":[{"v":"C"},{"v":0}]},{"c":[{"v":"D"},{"v":0}]},{"c":[{"v":"F"},{"v":0}]}]},"googleChartBar":{"cols":[{"id":"Class","label":"Class","type":"string"},{"id":"A","label":"A","type":"number"},{"id":"B","label":"B","type":"number"},{"id":"C","label":"C","type":"number"},{"id":"D","label":"D","type":"number"},{"id":"F","label":"F","type":"number"}],"rows":[{"c":[{"v":"Fall '14, Section 001"},{"v":51},{"v":2},{"v":0},{"v":0},{"v":0}]},{"c":[{"v":"Fall '13, Section 001"},{"v":32},{"v":1},{"v":0},{"v":0},{"v":0}]},{"c":[{"v":"Fall '12, Section 001"},{"v":34},{"v":1},{"v":0},{"v":0},{"v":0}]}]},"grades":{"A":{"raw":117,"percentage":"89.3%"},"B":{"raw":4,"percentage":"3.1%"},"C":{"raw":0,"percentage":"0%"},"D":{"raw":0,"percentage":"0%"},"F":{"raw":0,"percentage":"0%"},"S":{"raw":10,"percentage":"7.6%"},"U":{"raw":0,"percentage":"0%"},"IN":{"raw":0,"percentage":"0%"},"LA":{"raw":0,"percentage":"0%"},"AU":{"raw":0,"percentage":"0%"},"NR":{"raw":0,"percentage":"0%"},"W":{"raw":0,"percentage":"0%"},"TOTAL":{"raw":131,"percentage":"100%"}},"pieTitle":"Composite Grade Distribution for Selected Parameters","pieInfo":"Showing only letter grades"}}