{"individual":[{"courseName":"PO 590 - Section 601","courseId":"PO-590-601-2248","instructorName":"Oviedo-Rondon,Edgar Orlando","courseSem":"Fall '24","grades":{"A":{"raw":13,"percentage":"100%"},"B":{"raw":0,"percentage":"0%"},"C":{"raw":0,"percentage":"0%"},"D":{"raw":0,"percentage":"0%"},"F":{"raw":0,"percentage":"0%"},"S":{"raw":0,"percentage":"0%"},"U":{"raw":0,"percentage":"0%"},"IN":{"raw":0,"percentage":"0%"},"LA":{"raw":0,"percentage":"0%"},"AU":{"raw":0,"percentage":"0%"},"NR":{"raw":0,"percentage":"0%"},"W":{"raw":0,"percentage":"0%"},"TOTAL":{"raw":13,"percentage":"100%"}},"googleChart":{"cols":[{"id":"Name","label":"Name","type":"string"},{"id":"Value","label":"Value","type":"number"}],"rows":[{"c":[{"v":"A"},{"v":13}]},{"c":[{"v":"B"},{"v":0}]},{"c":[{"v":"C"},{"v":0}]},{"c":[{"v":"D"},{"v":0}]},{"c":[{"v":"F"},{"v":0}]},{"c":[{"v":"S"},{"v":0}]},{"c":[{"v":"U"},{"v":0}]},{"c":[{"v":"IN"},{"v":0}]},{"c":[{"v":"LA"},{"v":0}]},{"c":[{"v":"AU"},{"v":0}]},{"c":[{"v":"NR"},{"v":0}]},{"c":[{"v":"W"},{"v":0}]}]}},{"courseName":"PO 590 - Section 010","courseId":"PO-590-010-2238","instructorName":"Pullin,Allison","courseSem":"Fall '23","grades":{"A":{"raw":4,"percentage":"80%"},"B":{"raw":1,"percentage":"20%"},"C":{"raw":0,"percentage":"0%"},"D":{"raw":0,"percentage":"0%"},"F":{"raw":0,"percentage":"0%"},"S":{"raw":0,"percentage":"0%"},"U":{"raw":0,"percentage":"0%"},"IN":{"raw":0,"percentage":"0%"},"LA":{"raw":0,"percentage":"0%"},"AU":{"raw":0,"percentage":"0%"},"NR":{"raw":0,"percentage":"0%"},"W":{"raw":0,"percentage":"0%"},"TOTAL":{"raw":5,"percentage":"100%"}},"googleChart":{"cols":[{"id":"Name","label":"Name","type":"string"},{"id":"Value","label":"Value","type":"number"}],"rows":[{"c":[{"v":"A"},{"v":4}]},{"c":[{"v":"B"},{"v":1}]},{"c":[{"v":"C"},{"v":0}]},{"c":[{"v":"D"},{"v":0}]},{"c":[{"v":"F"},{"v":0}]},{"c":[{"v":"S"},{"v":0}]},{"c":[{"v":"U"},{"v":0}]},{"c":[{"v":"IN"},{"v":0}]},{"c":[{"v":"LA"},{"v":0}]},{"c":[{"v":"AU"},{"v":0}]},{"c":[{"v":"NR"},{"v":0}]},{"c":[{"v":"W"},{"v":0}]}]}},{"courseName":"PO 590 - Section 003","courseId":"PO-590-003-2231","instructorName":"Anderson,Kenneth E","courseSem":"Spring '23","grades":{"A":{"raw":8,"percentage":"100%"},"B":{"raw":0,"percentage":"0%"},"C":{"raw":0,"percentage":"0%"},"D":{"raw":0,"percentage":"0%"},"F":{"raw":0,"percentage":"0%"},"S":{"raw":0,"percentage":"0%"},"U":{"raw":0,"percentage":"0%"},"IN":{"raw":0,"percentage":"0%"},"LA":{"raw":0,"percentage":"0%"},"AU":{"raw":0,"percentage":"0%"},"NR":{"raw":0,"percentage":"0%"},"W":{"raw":0,"percentage":"0%"},"TOTAL":{"raw":8,"percentage":"100%"}},"googleChart":{"cols":[{"id":"Name","label":"Name","type":"string"},{"id":"Value","label":"Value","type":"number"}],"rows":[{"c":[{"v":"A"},{"v":8}]},{"c":[{"v":"B"},{"v":0}]},{"c":[{"v":"C"},{"v":0}]},{"c":[{"v":"D"},{"v":0}]},{"c":[{"v":"F"},{"v":0}]},{"c":[{"v":"S"},{"v":0}]},{"c":[{"v":"U"},{"v":0}]},{"c":[{"v":"IN"},{"v":0}]},{"c":[{"v":"LA"},{"v":0}]},{"c":[{"v":"AU"},{"v":0}]},{"c":[{"v":"NR"},{"v":0}]},{"c":[{"v":"W"},{"v":0}]}]}},{"courseName":"PO 590 - Section 601","courseId":"PO-590-601-2228","instructorName":"Oviedo-Rondon,Edgar Orlando","courseSem":"Fall '22","grades":{"A":{"raw":4,"percentage":"80%"},"B":{"raw":1,"percentage":"20%"},"C":{"raw":0,"percentage":"0%"},"D":{"raw":0,"percentage":"0%"},"F":{"raw":0,"percentage":"0%"},"S":{"raw":0,"percentage":"0%"},"U":{"raw":0,"percentage":"0%"},"IN":{"raw":0,"percentage":"0%"},"LA":{"raw":0,"percentage":"0%"},"AU":{"raw":0,"percentage":"0%"},"NR":{"raw":0,"percentage":"0%"},"W":{"raw":0,"percentage":"0%"},"TOTAL":{"raw":5,"percentage":"100%"}},"googleChart":{"cols":[{"id":"Name","label":"Name","type":"string"},{"id":"Value","label":"Value","type":"number"}],"rows":[{"c":[{"v":"A"},{"v":4}]},{"c":[{"v":"B"},{"v":1}]},{"c":[{"v":"C"},{"v":0}]},{"c":[{"v":"D"},{"v":0}]},{"c":[{"v":"F"},{"v":0}]},{"c":[{"v":"S"},{"v":0}]},{"c":[{"v":"U"},{"v":0}]},{"c":[{"v":"IN"},{"v":0}]},{"c":[{"v":"LA"},{"v":0}]},{"c":[{"v":"AU"},{"v":0}]},{"c":[{"v":"NR"},{"v":0}]},{"c":[{"v":"W"},{"v":0}]}]}},{"courseName":"PO 590 - Section 601","courseId":"PO-590-601-2221","instructorName":"Fahrenholz,Adam Charles","courseSem":"Spring '22","grades":{"A":{"raw":6,"percentage":"85.7%"},"B":{"raw":1,"percentage":"14.3%"},"C":{"raw":0,"percentage":"0%"},"D":{"raw":0,"percentage":"0%"},"F":{"raw":0,"percentage":"0%"},"S":{"raw":0,"percentage":"0%"},"U":{"raw":0,"percentage":"0%"},"IN":{"raw":0,"percentage":"0%"},"LA":{"raw":0,"percentage":"0%"},"AU":{"raw":0,"percentage":"0%"},"NR":{"raw":0,"percentage":"0%"},"W":{"raw":0,"percentage":"0%"},"TOTAL":{"raw":7,"percentage":"100%"}},"googleChart":{"cols":[{"id":"Name","label":"Name","type":"string"},{"id":"Value","label":"Value","type":"number"}],"rows":[{"c":[{"v":"A"},{"v":6}]},{"c":[{"v":"B"},{"v":1}]},{"c":[{"v":"C"},{"v":0}]},{"c":[{"v":"D"},{"v":0}]},{"c":[{"v":"F"},{"v":0}]},{"c":[{"v":"S"},{"v":0}]},{"c":[{"v":"U"},{"v":0}]},{"c":[{"v":"IN"},{"v":0}]},{"c":[{"v":"LA"},{"v":0}]},{"c":[{"v":"AU"},{"v":0}]},{"c":[{"v":"NR"},{"v":0}]},{"c":[{"v":"W"},{"v":0}]}]}},{"courseName":"PO 590 - Section 601","courseId":"PO-590-601-2211","instructorName":"Fahrenholz,Adam Charles","courseSem":"Spring '21","grades":{"A":{"raw":4,"percentage":"80%"},"B":{"raw":1,"percentage":"20%"},"C":{"raw":0,"percentage":"0%"},"D":{"raw":0,"percentage":"0%"},"F":{"raw":0,"percentage":"0%"},"S":{"raw":0,"percentage":"0%"},"U":{"raw":0,"percentage":"0%"},"IN":{"raw":0,"percentage":"0%"},"LA":{"raw":0,"percentage":"0%"},"AU":{"raw":0,"percentage":"0%"},"NR":{"raw":0,"percentage":"0%"},"W":{"raw":0,"percentage":"0%"},"TOTAL":{"raw":5,"percentage":"100%"}},"googleChart":{"cols":[{"id":"Name","label":"Name","type":"string"},{"id":"Value","label":"Value","type":"number"}],"rows":[{"c":[{"v":"A"},{"v":4}]},{"c":[{"v":"B"},{"v":1}]},{"c":[{"v":"C"},{"v":0}]},{"c":[{"v":"D"},{"v":0}]},{"c":[{"v":"F"},{"v":0}]},{"c":[{"v":"S"},{"v":0}]},{"c":[{"v":"U"},{"v":0}]},{"c":[{"v":"IN"},{"v":0}]},{"c":[{"v":"LA"},{"v":0}]},{"c":[{"v":"AU"},{"v":0}]},{"c":[{"v":"NR"},{"v":0}]},{"c":[{"v":"W"},{"v":0}]}]}},{"courseName":"PO 590 - Section 002","courseId":"PO-590-002-2198","instructorName":"Beckstead,Robert","courseSem":"Fall '19","grades":{"A":{"raw":0,"percentage":"0%"},"B":{"raw":0,"percentage":"0%"},"C":{"raw":0,"percentage":"0%"},"D":{"raw":0,"percentage":"0%"},"F":{"raw":0,"percentage":"0%"},"S":{"raw":0,"percentage":"0%"},"U":{"raw":0,"percentage":"0%"},"IN":{"raw":0,"percentage":"0%"},"LA":{"raw":5,"percentage":"100%"},"AU":{"raw":0,"percentage":"0%"},"NR":{"raw":0,"percentage":"0%"},"W":{"raw":0,"percentage":"0%"},"TOTAL":{"raw":5,"percentage":"100%"}},"googleChart":{"cols":[{"id":"Name","label":"Name","type":"string"},{"id":"Value","label":"Value","type":"number"}],"rows":[{"c":[{"v":"A"},{"v":0}]},{"c":[{"v":"B"},{"v":0}]},{"c":[{"v":"C"},{"v":0}]},{"c":[{"v":"D"},{"v":0}]},{"c":[{"v":"F"},{"v":0}]},{"c":[{"v":"S"},{"v":0}]},{"c":[{"v":"U"},{"v":0}]},{"c":[{"v":"IN"},{"v":0}]},{"c":[{"v":"LA"},{"v":5}]},{"c":[{"v":"AU"},{"v":0}]},{"c":[{"v":"NR"},{"v":0}]},{"c":[{"v":"W"},{"v":0}]}]}},{"courseName":"PO 590 - Section 007","courseId":"PO-590-007-2191","instructorName":"Carver,Donna K.","courseSem":"Spring '19","grades":{"A":{"raw":10,"percentage":"100%"},"B":{"raw":0,"percentage":"0%"},"C":{"raw":0,"percentage":"0%"},"D":{"raw":0,"percentage":"0%"},"F":{"raw":0,"percentage":"0%"},"S":{"raw":0,"percentage":"0%"},"U":{"raw":0,"percentage":"0%"},"IN":{"raw":0,"percentage":"0%"},"LA":{"raw":0,"percentage":"0%"},"AU":{"raw":0,"percentage":"0%"},"NR":{"raw":0,"percentage":"0%"},"W":{"raw":0,"percentage":"0%"},"TOTAL":{"raw":10,"percentage":"100%"}},"googleChart":{"cols":[{"id":"Name","label":"Name","type":"string"},{"id":"Value","label":"Value","type":"number"}],"rows":[{"c":[{"v":"A"},{"v":10}]},{"c":[{"v":"B"},{"v":0}]},{"c":[{"v":"C"},{"v":0}]},{"c":[{"v":"D"},{"v":0}]},{"c":[{"v":"F"},{"v":0}]},{"c":[{"v":"S"},{"v":0}]},{"c":[{"v":"U"},{"v":0}]},{"c":[{"v":"IN"},{"v":0}]},{"c":[{"v":"LA"},{"v":0}]},{"c":[{"v":"AU"},{"v":0}]},{"c":[{"v":"NR"},{"v":0}]},{"c":[{"v":"W"},{"v":0}]}]}},{"courseName":"PO 590 - Section 601","courseId":"PO-590-601-2191","instructorName":"Fahrenholz,Adam Charles","courseSem":"Spring '19","grades":{"A":{"raw":4,"percentage":"80%"},"B":{"raw":1,"percentage":"20%"},"C":{"raw":0,"percentage":"0%"},"D":{"raw":0,"percentage":"0%"},"F":{"raw":0,"percentage":"0%"},"S":{"raw":0,"percentage":"0%"},"U":{"raw":0,"percentage":"0%"},"IN":{"raw":0,"percentage":"0%"},"LA":{"raw":0,"percentage":"0%"},"AU":{"raw":0,"percentage":"0%"},"NR":{"raw":0,"percentage":"0%"},"W":{"raw":0,"percentage":"0%"},"TOTAL":{"raw":5,"percentage":"100%"}},"googleChart":{"cols":[{"id":"Name","label":"Name","type":"string"},{"id":"Value","label":"Value","type":"number"}],"rows":[{"c":[{"v":"A"},{"v":4}]},{"c":[{"v":"B"},{"v":1}]},{"c":[{"v":"C"},{"v":0}]},{"c":[{"v":"D"},{"v":0}]},{"c":[{"v":"F"},{"v":0}]},{"c":[{"v":"S"},{"v":0}]},{"c":[{"v":"U"},{"v":0}]},{"c":[{"v":"IN"},{"v":0}]},{"c":[{"v":"LA"},{"v":0}]},{"c":[{"v":"AU"},{"v":0}]},{"c":[{"v":"NR"},{"v":0}]},{"c":[{"v":"W"},{"v":0}]}]}},{"courseName":"PO 590 - Section 001","courseId":"PO-590-001-2188","instructorName":"Edens,Frank W.","courseSem":"Fall '18","grades":{"A":{"raw":6,"percentage":"100%"},"B":{"raw":0,"percentage":"0%"},"C":{"raw":0,"percentage":"0%"},"D":{"raw":0,"percentage":"0%"},"F":{"raw":0,"percentage":"0%"},"S":{"raw":0,"percentage":"0%"},"U":{"raw":0,"percentage":"0%"},"IN":{"raw":0,"percentage":"0%"},"LA":{"raw":0,"percentage":"0%"},"AU":{"raw":0,"percentage":"0%"},"NR":{"raw":0,"percentage":"0%"},"W":{"raw":0,"percentage":"0%"},"TOTAL":{"raw":6,"percentage":"100%"}},"googleChart":{"cols":[{"id":"Name","label":"Name","type":"string"},{"id":"Value","label":"Value","type":"number"}],"rows":[{"c":[{"v":"A"},{"v":6}]},{"c":[{"v":"B"},{"v":0}]},{"c":[{"v":"C"},{"v":0}]},{"c":[{"v":"D"},{"v":0}]},{"c":[{"v":"F"},{"v":0}]},{"c":[{"v":"S"},{"v":0}]},{"c":[{"v":"U"},{"v":0}]},{"c":[{"v":"IN"},{"v":0}]},{"c":[{"v":"LA"},{"v":0}]},{"c":[{"v":"AU"},{"v":0}]},{"c":[{"v":"NR"},{"v":0}]},{"c":[{"v":"W"},{"v":0}]}]}},{"courseName":"PO 590 - Section 001","courseId":"PO-590-001-2161","instructorName":"Brake,John Thomas","courseSem":"Spring '16","grades":{"A":{"raw":3,"percentage":"42.9%"},"B":{"raw":4,"percentage":"57.1%"},"C":{"raw":0,"percentage":"0%"},"D":{"raw":0,"percentage":"0%"},"F":{"raw":0,"percentage":"0%"},"S":{"raw":0,"percentage":"0%"},"U":{"raw":0,"percentage":"0%"},"IN":{"raw":0,"percentage":"0%"},"LA":{"raw":0,"percentage":"0%"},"AU":{"raw":0,"percentage":"0%"},"NR":{"raw":0,"percentage":"0%"},"W":{"raw":0,"percentage":"0%"},"TOTAL":{"raw":7,"percentage":"100%"}},"googleChart":{"cols":[{"id":"Name","label":"Name","type":"string"},{"id":"Value","label":"Value","type":"number"}],"rows":[{"c":[{"v":"A"},{"v":3}]},{"c":[{"v":"B"},{"v":4}]},{"c":[{"v":"C"},{"v":0}]},{"c":[{"v":"D"},{"v":0}]},{"c":[{"v":"F"},{"v":0}]},{"c":[{"v":"S"},{"v":0}]},{"c":[{"v":"U"},{"v":0}]},{"c":[{"v":"IN"},{"v":0}]},{"c":[{"v":"LA"},{"v":0}]},{"c":[{"v":"AU"},{"v":0}]},{"c":[{"v":"NR"},{"v":0}]},{"c":[{"v":"W"},{"v":0}]}]}}],"composite":{"googleChartPie":{"cols":[{"id":"Name","label":"Name","type":"string"},{"id":"Value","label":"Value","type":"number"}],"rows":[{"c":[{"v":"A"},{"v":62}]},{"c":[{"v":"B"},{"v":9}]},{"c":[{"v":"C"},{"v":0}]},{"c":[{"v":"D"},{"v":0}]},{"c":[{"v":"F"},{"v":0}]}]},"googleChartBar":{"cols":[{"id":"Class","label":"Class","type":"string"},{"id":"A","label":"A","type":"number"},{"id":"B","label":"B","type":"number"},{"id":"C","label":"C","type":"number"},{"id":"D","label":"D","type":"number"},{"id":"F","label":"F","type":"number"}],"rows":[{"c":[{"v":"Fall '24, Section 601"},{"v":13},{"v":0},{"v":0},{"v":0},{"v":0}]},{"c":[{"v":"Fall '23, Section 010"},{"v":4},{"v":1},{"v":0},{"v":0},{"v":0}]},{"c":[{"v":"Spring '23, Section 003"},{"v":8},{"v":0},{"v":0},{"v":0},{"v":0}]},{"c":[{"v":"Fall '22, Section 601"},{"v":4},{"v":1},{"v":0},{"v":0},{"v":0}]},{"c":[{"v":"Spring '22, Section 601"},{"v":6},{"v":1},{"v":0},{"v":0},{"v":0}]},{"c":[{"v":"Spring '21, Section 601"},{"v":4},{"v":1},{"v":0},{"v":0},{"v":0}]},{"c":[{"v":"Fall '19, Section 002"},{"v":0},{"v":0},{"v":0},{"v":0},{"v":0}]},{"c":[{"v":"Spring '19, Section 007"},{"v":10},{"v":0},{"v":0},{"v":0},{"v":0}]},{"c":[{"v":"Spring '19, Section 601"},{"v":4},{"v":1},{"v":0},{"v":0},{"v":0}]},{"c":[{"v":"Fall '18, Section 001"},{"v":6},{"v":0},{"v":0},{"v":0},{"v":0}]},{"c":[{"v":"Spring '16, Section 001"},{"v":3},{"v":4},{"v":0},{"v":0},{"v":0}]}]},"grades":{"A":{"raw":62,"percentage":"81.6%"},"B":{"raw":9,"percentage":"11.8%"},"C":{"raw":0,"percentage":"0%"},"D":{"raw":0,"percentage":"0%"},"F":{"raw":0,"percentage":"0%"},"S":{"raw":0,"percentage":"0%"},"U":{"raw":0,"percentage":"0%"},"IN":{"raw":0,"percentage":"0%"},"LA":{"raw":5,"percentage":"6.6%"},"AU":{"raw":0,"percentage":"0%"},"NR":{"raw":0,"percentage":"0%"},"W":{"raw":0,"percentage":"0%"},"TOTAL":{"raw":76,"percentage":"100%"}},"pieTitle":"Composite Grade Distribution for Selected Parameters","pieInfo":"Showing only letter grades"}}