{"individual":[{"courseName":"BSC 546 - Section 601","courseId":"BSC-546-601-2226","instructorName":"Johnstone III,William Miller","courseSem":"Summer I '22","grades":{"A":{"raw":28,"percentage":"93.3%"},"B":{"raw":0,"percentage":"0%"},"C":{"raw":0,"percentage":"0%"},"D":{"raw":0,"percentage":"0%"},"F":{"raw":0,"percentage":"0%"},"S":{"raw":0,"percentage":"0%"},"U":{"raw":0,"percentage":"0%"},"IN":{"raw":1,"percentage":"3.3%"},"LA":{"raw":0,"percentage":"0%"},"AU":{"raw":0,"percentage":"0%"},"NR":{"raw":0,"percentage":"0%"},"W":{"raw":1,"percentage":"3.3%"},"TOTAL":{"raw":30,"percentage":"100%"}},"googleChart":{"cols":[{"id":"Name","label":"Name","type":"string"},{"id":"Value","label":"Value","type":"number"}],"rows":[{"c":[{"v":"A"},{"v":28}]},{"c":[{"v":"B"},{"v":0}]},{"c":[{"v":"C"},{"v":0}]},{"c":[{"v":"D"},{"v":0}]},{"c":[{"v":"F"},{"v":0}]},{"c":[{"v":"S"},{"v":0}]},{"c":[{"v":"U"},{"v":0}]},{"c":[{"v":"IN"},{"v":1}]},{"c":[{"v":"LA"},{"v":0}]},{"c":[{"v":"AU"},{"v":0}]},{"c":[{"v":"NR"},{"v":0}]},{"c":[{"v":"W"},{"v":1}]}]}},{"courseName":"BSC 546 - Section 601","courseId":"BSC-546-601-2218","instructorName":"Johnstone III,William Miller","courseSem":"Fall '21","grades":{"A":{"raw":28,"percentage":"90.3%"},"B":{"raw":2,"percentage":"6.5%"},"C":{"raw":0,"percentage":"0%"},"D":{"raw":0,"percentage":"0%"},"F":{"raw":0,"percentage":"0%"},"S":{"raw":0,"percentage":"0%"},"U":{"raw":0,"percentage":"0%"},"IN":{"raw":0,"percentage":"0%"},"LA":{"raw":0,"percentage":"0%"},"AU":{"raw":0,"percentage":"0%"},"NR":{"raw":0,"percentage":"0%"},"W":{"raw":1,"percentage":"3.2%"},"TOTAL":{"raw":31,"percentage":"100%"}},"googleChart":{"cols":[{"id":"Name","label":"Name","type":"string"},{"id":"Value","label":"Value","type":"number"}],"rows":[{"c":[{"v":"A"},{"v":28}]},{"c":[{"v":"B"},{"v":2}]},{"c":[{"v":"C"},{"v":0}]},{"c":[{"v":"D"},{"v":0}]},{"c":[{"v":"F"},{"v":0}]},{"c":[{"v":"S"},{"v":0}]},{"c":[{"v":"U"},{"v":0}]},{"c":[{"v":"IN"},{"v":0}]},{"c":[{"v":"LA"},{"v":0}]},{"c":[{"v":"AU"},{"v":0}]},{"c":[{"v":"NR"},{"v":0}]},{"c":[{"v":"W"},{"v":1}]}]}},{"courseName":"BSC 546 - Section 601","courseId":"BSC-546-601-2217","instructorName":"Johnstone III,William Miller","courseSem":"Summer II '21","grades":{"A":{"raw":0,"percentage":"0%"},"B":{"raw":0,"percentage":"0%"},"C":{"raw":0,"percentage":"0%"},"D":{"raw":0,"percentage":"0%"},"F":{"raw":0,"percentage":"0%"},"S":{"raw":0,"percentage":"0%"},"U":{"raw":0,"percentage":"0%"},"IN":{"raw":0,"percentage":"0%"},"LA":{"raw":7,"percentage":"87.5%"},"AU":{"raw":0,"percentage":"0%"},"NR":{"raw":0,"percentage":"0%"},"W":{"raw":1,"percentage":"12.5%"},"TOTAL":{"raw":8,"percentage":"100%"}},"googleChart":{"cols":[{"id":"Name","label":"Name","type":"string"},{"id":"Value","label":"Value","type":"number"}],"rows":[{"c":[{"v":"A"},{"v":0}]},{"c":[{"v":"B"},{"v":0}]},{"c":[{"v":"C"},{"v":0}]},{"c":[{"v":"D"},{"v":0}]},{"c":[{"v":"F"},{"v":0}]},{"c":[{"v":"S"},{"v":0}]},{"c":[{"v":"U"},{"v":0}]},{"c":[{"v":"IN"},{"v":0}]},{"c":[{"v":"LA"},{"v":7}]},{"c":[{"v":"AU"},{"v":0}]},{"c":[{"v":"NR"},{"v":0}]},{"c":[{"v":"W"},{"v":1}]}]}},{"courseName":"BSC 546 - Section 601","courseId":"BSC-546-601-2216","instructorName":"Johnstone III,William Miller","courseSem":"Summer I '21","grades":{"A":{"raw":20,"percentage":"90.9%"},"B":{"raw":1,"percentage":"4.5%"},"C":{"raw":0,"percentage":"0%"},"D":{"raw":0,"percentage":"0%"},"F":{"raw":0,"percentage":"0%"},"S":{"raw":0,"percentage":"0%"},"U":{"raw":0,"percentage":"0%"},"IN":{"raw":1,"percentage":"4.5%"},"LA":{"raw":0,"percentage":"0%"},"AU":{"raw":0,"percentage":"0%"},"NR":{"raw":0,"percentage":"0%"},"W":{"raw":0,"percentage":"0%"},"TOTAL":{"raw":22,"percentage":"100%"}},"googleChart":{"cols":[{"id":"Name","label":"Name","type":"string"},{"id":"Value","label":"Value","type":"number"}],"rows":[{"c":[{"v":"A"},{"v":20}]},{"c":[{"v":"B"},{"v":1}]},{"c":[{"v":"C"},{"v":0}]},{"c":[{"v":"D"},{"v":0}]},{"c":[{"v":"F"},{"v":0}]},{"c":[{"v":"S"},{"v":0}]},{"c":[{"v":"U"},{"v":0}]},{"c":[{"v":"IN"},{"v":1}]},{"c":[{"v":"LA"},{"v":0}]},{"c":[{"v":"AU"},{"v":0}]},{"c":[{"v":"NR"},{"v":0}]},{"c":[{"v":"W"},{"v":0}]}]}},{"courseName":"BSC 546 - Section 601","courseId":"BSC-546-601-2208","instructorName":"Johnstone III,William Miller","courseSem":"Fall '20","grades":{"A":{"raw":21,"percentage":"100%"},"B":{"raw":0,"percentage":"0%"},"C":{"raw":0,"percentage":"0%"},"D":{"raw":0,"percentage":"0%"},"F":{"raw":0,"percentage":"0%"},"S":{"raw":0,"percentage":"0%"},"U":{"raw":0,"percentage":"0%"},"IN":{"raw":0,"percentage":"0%"},"LA":{"raw":0,"percentage":"0%"},"AU":{"raw":0,"percentage":"0%"},"NR":{"raw":0,"percentage":"0%"},"W":{"raw":0,"percentage":"0%"},"TOTAL":{"raw":21,"percentage":"100%"}},"googleChart":{"cols":[{"id":"Name","label":"Name","type":"string"},{"id":"Value","label":"Value","type":"number"}],"rows":[{"c":[{"v":"A"},{"v":21}]},{"c":[{"v":"B"},{"v":0}]},{"c":[{"v":"C"},{"v":0}]},{"c":[{"v":"D"},{"v":0}]},{"c":[{"v":"F"},{"v":0}]},{"c":[{"v":"S"},{"v":0}]},{"c":[{"v":"U"},{"v":0}]},{"c":[{"v":"IN"},{"v":0}]},{"c":[{"v":"LA"},{"v":0}]},{"c":[{"v":"AU"},{"v":0}]},{"c":[{"v":"NR"},{"v":0}]},{"c":[{"v":"W"},{"v":0}]}]}},{"courseName":"BSC 546 - Section 601","courseId":"BSC-546-601-2206","instructorName":"Johnstone III,William Miller","courseSem":"Summer I '20","grades":{"A":{"raw":18,"percentage":"100%"},"B":{"raw":0,"percentage":"0%"},"C":{"raw":0,"percentage":"0%"},"D":{"raw":0,"percentage":"0%"},"F":{"raw":0,"percentage":"0%"},"S":{"raw":0,"percentage":"0%"},"U":{"raw":0,"percentage":"0%"},"IN":{"raw":0,"percentage":"0%"},"LA":{"raw":0,"percentage":"0%"},"AU":{"raw":0,"percentage":"0%"},"NR":{"raw":0,"percentage":"0%"},"W":{"raw":0,"percentage":"0%"},"TOTAL":{"raw":18,"percentage":"100%"}},"googleChart":{"cols":[{"id":"Name","label":"Name","type":"string"},{"id":"Value","label":"Value","type":"number"}],"rows":[{"c":[{"v":"A"},{"v":18}]},{"c":[{"v":"B"},{"v":0}]},{"c":[{"v":"C"},{"v":0}]},{"c":[{"v":"D"},{"v":0}]},{"c":[{"v":"F"},{"v":0}]},{"c":[{"v":"S"},{"v":0}]},{"c":[{"v":"U"},{"v":0}]},{"c":[{"v":"IN"},{"v":0}]},{"c":[{"v":"LA"},{"v":0}]},{"c":[{"v":"AU"},{"v":0}]},{"c":[{"v":"NR"},{"v":0}]},{"c":[{"v":"W"},{"v":0}]}]}},{"courseName":"BSC 546 - Section 601","courseId":"BSC-546-601-2201","instructorName":"Johnstone III,William Miller","courseSem":"Spring '20","grades":{"A":{"raw":22,"percentage":"91.7%"},"B":{"raw":0,"percentage":"0%"},"C":{"raw":0,"percentage":"0%"},"D":{"raw":0,"percentage":"0%"},"F":{"raw":0,"percentage":"0%"},"S":{"raw":0,"percentage":"0%"},"U":{"raw":0,"percentage":"0%"},"IN":{"raw":2,"percentage":"8.3%"},"LA":{"raw":0,"percentage":"0%"},"AU":{"raw":0,"percentage":"0%"},"NR":{"raw":0,"percentage":"0%"},"W":{"raw":0,"percentage":"0%"},"TOTAL":{"raw":24,"percentage":"100%"}},"googleChart":{"cols":[{"id":"Name","label":"Name","type":"string"},{"id":"Value","label":"Value","type":"number"}],"rows":[{"c":[{"v":"A"},{"v":22}]},{"c":[{"v":"B"},{"v":0}]},{"c":[{"v":"C"},{"v":0}]},{"c":[{"v":"D"},{"v":0}]},{"c":[{"v":"F"},{"v":0}]},{"c":[{"v":"S"},{"v":0}]},{"c":[{"v":"U"},{"v":0}]},{"c":[{"v":"IN"},{"v":2}]},{"c":[{"v":"LA"},{"v":0}]},{"c":[{"v":"AU"},{"v":0}]},{"c":[{"v":"NR"},{"v":0}]},{"c":[{"v":"W"},{"v":0}]}]}},{"courseName":"BSC 546 - Section 601","courseId":"BSC-546-601-2197","instructorName":"Johnstone III,William Miller","courseSem":"Summer II '19","grades":{"A":{"raw":0,"percentage":"0%"},"B":{"raw":0,"percentage":"0%"},"C":{"raw":0,"percentage":"0%"},"D":{"raw":0,"percentage":"0%"},"F":{"raw":0,"percentage":"0%"},"S":{"raw":0,"percentage":"0%"},"U":{"raw":0,"percentage":"0%"},"IN":{"raw":0,"percentage":"0%"},"LA":{"raw":15,"percentage":"100%"},"AU":{"raw":0,"percentage":"0%"},"NR":{"raw":0,"percentage":"0%"},"W":{"raw":0,"percentage":"0%"},"TOTAL":{"raw":15,"percentage":"100%"}},"googleChart":{"cols":[{"id":"Name","label":"Name","type":"string"},{"id":"Value","label":"Value","type":"number"}],"rows":[{"c":[{"v":"A"},{"v":0}]},{"c":[{"v":"B"},{"v":0}]},{"c":[{"v":"C"},{"v":0}]},{"c":[{"v":"D"},{"v":0}]},{"c":[{"v":"F"},{"v":0}]},{"c":[{"v":"S"},{"v":0}]},{"c":[{"v":"U"},{"v":0}]},{"c":[{"v":"IN"},{"v":0}]},{"c":[{"v":"LA"},{"v":15}]},{"c":[{"v":"AU"},{"v":0}]},{"c":[{"v":"NR"},{"v":0}]},{"c":[{"v":"W"},{"v":0}]}]}},{"courseName":"BSC 546 - Section 601","courseId":"BSC-546-601-2196","instructorName":"Johnstone III,William Miller","courseSem":"Summer I '19","grades":{"A":{"raw":19,"percentage":"82.6%"},"B":{"raw":3,"percentage":"13%"},"C":{"raw":0,"percentage":"0%"},"D":{"raw":0,"percentage":"0%"},"F":{"raw":0,"percentage":"0%"},"S":{"raw":0,"percentage":"0%"},"U":{"raw":0,"percentage":"0%"},"IN":{"raw":1,"percentage":"4.3%"},"LA":{"raw":0,"percentage":"0%"},"AU":{"raw":0,"percentage":"0%"},"NR":{"raw":0,"percentage":"0%"},"W":{"raw":0,"percentage":"0%"},"TOTAL":{"raw":23,"percentage":"100%"}},"googleChart":{"cols":[{"id":"Name","label":"Name","type":"string"},{"id":"Value","label":"Value","type":"number"}],"rows":[{"c":[{"v":"A"},{"v":19}]},{"c":[{"v":"B"},{"v":3}]},{"c":[{"v":"C"},{"v":0}]},{"c":[{"v":"D"},{"v":0}]},{"c":[{"v":"F"},{"v":0}]},{"c":[{"v":"S"},{"v":0}]},{"c":[{"v":"U"},{"v":0}]},{"c":[{"v":"IN"},{"v":1}]},{"c":[{"v":"LA"},{"v":0}]},{"c":[{"v":"AU"},{"v":0}]},{"c":[{"v":"NR"},{"v":0}]},{"c":[{"v":"W"},{"v":0}]}]}}],"composite":{"googleChartPie":{"cols":[{"id":"Name","label":"Name","type":"string"},{"id":"Value","label":"Value","type":"number"}],"rows":[{"c":[{"v":"A"},{"v":156}]},{"c":[{"v":"B"},{"v":6}]},{"c":[{"v":"C"},{"v":0}]},{"c":[{"v":"D"},{"v":0}]},{"c":[{"v":"F"},{"v":0}]}]},"googleChartBar":{"cols":[{"id":"Class","label":"Class","type":"string"},{"id":"A","label":"A","type":"number"},{"id":"B","label":"B","type":"number"},{"id":"C","label":"C","type":"number"},{"id":"D","label":"D","type":"number"},{"id":"F","label":"F","type":"number"}],"rows":[{"c":[{"v":"Summer I '22, Section 601"},{"v":28},{"v":0},{"v":0},{"v":0},{"v":0}]},{"c":[{"v":"Fall '21, Section 601"},{"v":28},{"v":2},{"v":0},{"v":0},{"v":0}]},{"c":[{"v":"Summer II '21, Section 601"},{"v":0},{"v":0},{"v":0},{"v":0},{"v":0}]},{"c":[{"v":"Summer I '21, Section 601"},{"v":20},{"v":1},{"v":0},{"v":0},{"v":0}]},{"c":[{"v":"Fall '20, Section 601"},{"v":21},{"v":0},{"v":0},{"v":0},{"v":0}]},{"c":[{"v":"Summer I '20, Section 601"},{"v":18},{"v":0},{"v":0},{"v":0},{"v":0}]},{"c":[{"v":"Spring '20, Section 601"},{"v":22},{"v":0},{"v":0},{"v":0},{"v":0}]},{"c":[{"v":"Summer II '19, Section 601"},{"v":0},{"v":0},{"v":0},{"v":0},{"v":0}]},{"c":[{"v":"Summer I '19, Section 601"},{"v":19},{"v":3},{"v":0},{"v":0},{"v":0}]}]},"grades":{"A":{"raw":156,"percentage":"81.3%"},"B":{"raw":6,"percentage":"3.1%"},"C":{"raw":0,"percentage":"0%"},"D":{"raw":0,"percentage":"0%"},"F":{"raw":0,"percentage":"0%"},"S":{"raw":0,"percentage":"0%"},"U":{"raw":0,"percentage":"0%"},"IN":{"raw":5,"percentage":"2.6%"},"LA":{"raw":22,"percentage":"11.5%"},"AU":{"raw":0,"percentage":"0%"},"NR":{"raw":0,"percentage":"0%"},"W":{"raw":3,"percentage":"1.6%"},"TOTAL":{"raw":192,"percentage":"100%"}},"pieTitle":"Composite Grade Distribution for Selected Parameters","pieInfo":"Showing only letter grades"}}