{"instructors":[{"id":1391,"unity_id":"dlbarto2","name":"Barton,Donna"},{"id":6108,"unity_id":"xjjeng","name":"Jeng,Xinge Jessie"},{"id":3267,"unity_id":"kkyriak","name":"Kyriakoulis,Konstantinos"},{"id":2387,"unity_id":"jbpost2","name":"Post,Justin Blaise"},{"id":4833,"unity_id":"rdwoodar","name":"Woodard,Roger"},{"id":1841,"unity_id":"fawrigh2","name":"Wright,Fred Andrew"}],"years":["2024","2023","2022","2021","2020","2019","2018","2017","2016","2015","2014","2013","2012"],"sems":[{"value":"1","text":"Spring"},{"value":"8","text":"Fall"}]}