{"instructors":[{"id":1941,"unity_id":"gblank","name":"Blank,Gary B."},{"id":2191,"unity_id":"hmc","name":"Cheshire,Heather Mcrae"},{"id":1161,"unity_id":"cubbage","name":"Cubbage,Frederick Willis"},{"id":2771,"unity_id":"jmgray2","name":"Gray,Josh M"},{"id":6663,"unity_id":"jkern","name":"Kern,Jordan"},{"id":6180,"unity_id":"zholmes","name":"Leggett,Zakiya Holmes"},{"id":4257,"unity_id":"mrmchale","name":"McHale,Melissa R"},{"id":3782,"unity_id":"mamegalo","name":"Megalos,Mark Arthur"},{"id":1665,"unity_id":"egnichol","name":"Nichols,Elizabeth Guthrie"},{"id":5280,"unity_id":"sills","name":"Sills,Erin O'Donnell"},{"id":5572,"unity_id":"stwarren","name":"Warren,Sarah Timberlake"}],"years":["2024","2023","2020","2019","2018","2017","2016","2015","2014","2013","2012"],"sems":[{"value":"1","text":"Spring"},{"value":"8","text":"Fall"}]}