{"instructors":[{"id":2227,"unity_id":"hsarmstr","name":"Armstrong,Helen Saunders"},{"id":1791,"unity_id":"ercrosby","name":"Crosby,Eric Robert"},{"id":1414,"unity_id":"dmcrisp","name":"Gonzales Crisp,Denise"},{"id":220,"unity_id":"akhowar4","name":"Howard,Amber Kristine"},{"id":5571,"unity_id":"sttwn","name":"Townsend,Scott"},{"id":4866,"unity_id":"revuchni","name":"Vuchnich,Robin"}],"years":["2018","2017","2016","2015","2014","2013","2012","2011","2010","2009"],"sems":[{"value":"8","text":"Fall"}]}