{"instructors":[{"id":2128,"unity_id":"hdakroyd","name":"Akroyd,Duane"},{"id":3239,"unity_id":"kjashton","name":"Ashton,Kasey Jean"},{"id":5290,"unity_id":"sjbracke","name":"Barcinas PhD,Susan J"},{"id":6679,"unity_id":"kwbarr","name":"Barr,Krispin Wagoner"},{"id":3919,"unity_id":"mebartle","name":"Bartlett,Michelle E"},{"id":5714,"unity_id":"tjdavis4","name":"Davis,Tiffany Juanita"},{"id":1234,"unity_id":"dbdeardo","name":"Deardorff,Darla Kay"},{"id":2517,"unity_id":"jellis3","name":"Ellis PhD,James M"},{"id":2566,"unity_id":"jggayles","name":"Gayles,Joy Gaston"},{"id":861,"unity_id":"cdhoggan","name":"Hoggan,Chad David"},{"id":193,"unity_id":"ajjaeger","name":"Jaeger,Audrey J."},{"id":3155,"unity_id":"kdlohr","name":"Lohr,Kathy Diane"},{"id":1916,"unity_id":"fwlyons","name":"Lyons,Frankie Woodard"},{"id":8885,"unity_id":"kmmcgui3","name":"McGuire,Keon Monte"},{"id":701,"unity_id":"brad_m","name":"Mehlenbacher,Bradley S"},{"id":503,"unity_id":"baolson","name":"Olson,Barry A"},{"id":6394,"unity_id":"dlpittm2","name":"Pittman,David Lawrence"},{"id":343,"unity_id":"anbryan2","name":"Rockenbach,Alyssa Nicole"},{"id":6448,"unity_id":"ctraver","name":"Travers PhD,Christopher Steven"},{"id":4614,"unity_id":"pdumbach","name":"Umbach,Paul David"},{"id":1010,"unity_id":"clwarren","name":"Warren,Carrol Lynn"},{"id":6624,"unity_id":"mewhatle","name":"Whatley,Melissa Erin"}],"years":["2024","2023","2022","2021","2020","2019","2018","2017","2016","2015","2014","2013","2012","2011","2010","2009"],"sems":[{"value":"1","text":"Spring"},{"value":"8","text":"Fall"},{"value":"6","text":"Summer I"},{"value":"7","text":"Summer II"}]}