{"instructors":[{"id":4097,"unity_id":"mlbellam","name":"Bellamy,Mary Louise"},{"id":4236,"unity_id":"mrblanch","name":"Blanchard,Meg"},{"id":1083,"unity_id":"cpedging","name":"Edgington,Cyndi"},{"id":5601,"unity_id":"syholmes","name":"Holmes,Shawn Yvette"},{"id":6985,"unity_id":"wmreynol","name":"Reynolds,Matt"},{"id":4685,"unity_id":"pmshumak","name":"Shumaker Jeffrey,Penny Michelle"},{"id":4625,"unity_id":"pesimmon","name":"Simmons,Patricia E"}],"years":["2024","2023","2022","2021","2020","2017","2016","2015","2014","2013","2011","2010","2009"],"sems":[{"value":"1","text":"Spring"},{"value":"8","text":"Fall"}]}